taxonompy/__init__.py
taxonompy/taxon.py
taxonompy/parser/__init__.py
taxonompy/parser/xmlparser.py
taxonompy-1.0.0.dist-info/LICENSE
taxonompy-1.0.0.dist-info/METADATA
taxonompy-1.0.0.dist-info/WHEEL
taxonompy-1.0.0.dist-info/top_level.txt
taxonompy-1.0.0.dist-info/RECORD
